nejgit/__init__.py
nejgit/scripts/__init__.py
nejgit/scripts/canonical_path.py
nejgit/scripts/current_branch.py
nejgit/scripts/log.py
nejgit/scripts/meld.py
nejgit-0.1.dist-info/DESCRIPTION.rst
nejgit-0.1.dist-info/METADATA
nejgit-0.1.dist-info/RECORD
nejgit-0.1.dist-info/WHEEL
nejgit-0.1.dist-info/entry_points.txt
nejgit-0.1.dist-info/metadata.json
nejgit-0.1.dist-info/top_level.txt
