Metadata-Version: 2.0
Name: nejgit
Version: 0.1
Summary: A collection of nejucomo's git helper tools.
Home-page: https://github.com/nejucomo/nejgit
Author: Nathan Wilcox
Author-email: nejucomo@gmail.com
License: GPLv3
Platform: UNKNOWN
